mcp_client_for_ollama/__init__.py
mcp_client_for_ollama/__main__.py
mcp_client_for_ollama/cli.py
mcp_client_for_ollama/client.py
mcp_client_for_ollama/config/__init__.py
mcp_client_for_ollama/config/defaults.py
mcp_client_for_ollama/config/manager.py
mcp_client_for_ollama/models/__init__.py
mcp_client_for_ollama/models/config_manager.py
mcp_client_for_ollama/models/manager.py
mcp_client_for_ollama/prompts/__init__.py
mcp_client_for_ollama/prompts/content.py
mcp_client_for_ollama/prompts/display.py
mcp_client_for_ollama/prompts/handler.py
mcp_client_for_ollama/prompts/injection.py
mcp_client_for_ollama/prompts/manager.py
mcp_client_for_ollama/server/__init__.py
mcp_client_for_ollama/server/connector.py
mcp_client_for_ollama/server/discovery.py
mcp_client_for_ollama/tools/__init__.py
mcp_client_for_ollama/tools/manager.py
mcp_client_for_ollama/utils/__init__.py
mcp_client_for_ollama/utils/connection.py
mcp_client_for_ollama/utils/constants.py
mcp_client_for_ollama/utils/fzf_style_completion.py
mcp_client_for_ollama/utils/hil_manager.py
mcp_client_for_ollama/utils/history.py
mcp_client_for_ollama/utils/input.py
mcp_client_for_ollama/utils/metrics.py
mcp_client_for_ollama/utils/streaming.py
mcp_client_for_ollama/utils/tool_display.py
mcp_client_for_ollama/utils/version.py
mcp_client_for_ollama-0.26.0.dist-info/licenses/LICENSE
mcp_client_for_ollama-0.26.0.dist-info/METADATA
mcp_client_for_ollama-0.26.0.dist-info/WHEEL
mcp_client_for_ollama-0.26.0.dist-info/entry_points.txt
mcp_client_for_ollama-0.26.0.dist-info/top_level.txt
mcp_client_for_ollama-0.26.0.dist-info/RECORD
