Metadata-Version: 2.4
Name: mcp-client-for-ollama
Version: 0.26.0
Summary: MCP Client for Ollama - A client for connecting to Model Context Protocol servers using Ollama
Author: Jonathan Löwenstern
License-Expression: MIT
Project-URL: Homepage, https://github.com/jonigl/mcp-client-for-ollama
Project-URL: Issues, https://github.com/jonigl/mcp-client-for-ollama/issues
Requires-Python: >=3.10
License-File: LICENSE
Requires-Dist: mcp~=1.25.0
Requires-Dist: ollama~=0.6.0
Requires-Dist: prompt-toolkit~=3.0.52
Requires-Dist: rich~=14.2.0
Requires-Dist: typer~=0.21.0
Dynamic: license-file
